docxl/__init__.py
docxl-0.0.0.dist-info/LICENSE
docxl-0.0.0.dist-info/METADATA
docxl-0.0.0.dist-info/WHEEL
docxl-0.0.0.dist-info/top_level.txt
docxl-0.0.0.dist-info/RECORD
