Metadata-Version: 2.1
Name: docxl
Version: 0.0.0
Summary: Convert docx or docx to excel formats
Home-page: https://github.com/RishabhBhatnagar/docxl
Author: Rishabh Bhatnagar
Author-email: bhatnagarrishabh4@gmail.com
License: UNKNOWN
Platform: UNKNOWN
Classifier: Programming Language :: Python :: 3
Classifier: License :: OSI Approved :: MIT License
Classifier: Operating System :: OS Independent
